marginpy-0.1.0a2.dist-info/METADATA
marginpy-0.1.0a2.dist-info/WHEEL
marginpy-0.1.0a2.dist-info/license_files/LICENSE
marginpy/bank.py
marginpy/types.py
marginpy/idl.json
marginpy/config.py
marginpy/logger.py
marginpy/group.py
marginpy/account.py
marginpy/client.py
marginpy/marginpy/py.typed
marginpy/marginpy/utp_observation/__init__.pyi
marginpy/marginpy/utp_observation/zo.pyi
marginpy/marginpy/utp_observation/mango.pyi
marginpy/marginpy/__init__.pyi
marginpy/utils/pda.py
marginpy/utils/misc.py
marginpy/utils/data_conversion.py
marginpy/utils/__init__.py
marginpy/utils/instructions.py
marginpy/generated_client/program_id.py
marginpy/generated_client/types/utp_zo_place_perp_order_ix_args.py
marginpy/generated_client/types/bank.py
marginpy/generated_client/types/group_config.py
marginpy/generated_client/types/order_type.py
marginpy/generated_client/types/mango_order_type.py
marginpy/generated_client/types/internal_transfer_type.py
marginpy/generated_client/types/utp_mango_place_perp_order_args.py
marginpy/generated_client/types/mango_side.py
marginpy/generated_client/types/mango_expiry_type.py
marginpy/generated_client/types/wrapped_i80f48.py
marginpy/generated_client/types/utp_account_config.py
marginpy/generated_client/types/bank_vault_type.py
marginpy/generated_client/types/utp_zo_cancel_perp_order_ix_args.py
marginpy/generated_client/types/lending_side.py
marginpy/generated_client/types/utp_config.py
marginpy/generated_client/types/margin_requirement.py
marginpy/generated_client/types/bank_config.py
marginpy/generated_client/types/equity_type.py
marginpy/generated_client/types/__init__.py
marginpy/generated_client/accounts/marginfi_account.py
marginpy/generated_client/accounts/marginfi_group.py
marginpy/generated_client/accounts/state.py
marginpy/generated_client/accounts/__init__.py
marginpy/generated_client/errors/anchor.py
marginpy/generated_client/errors/__init__.py
marginpy/generated_client/errors/custom.py
marginpy/generated_client/__init__.py
marginpy/generated_client/instructions/bank_fee_vault_withdraw.py
marginpy-0.1.0a2.dist-info/RECORD
