Metadata-Version: 2.1
Name: marginpy
Version: 0.1.0a2
Classifier: Programming Language :: Rust
Classifier: Programming Language :: Python :: Implementation :: CPython
Classifier: Programming Language :: Python :: Implementation :: PyPy
Requires-Dist: borsh-construct
Requires-Dist: anchorpy>=0.9.4
Requires-Dist: solana>=0.25.0
Requires-Dist: buffer>=0.2.1
Requires-Dist: construct>=2.10.67
Requires-Dist: tmp-patch-mango-explorer>=3.4.9
Requires-Dist: python-dotenv>=0.20.0
Requires-Dist: coloredlogs>=15.0.1
License-File: LICENSE
Summary: marginfi Python SDK
Keywords: marginfi,sdk
Author: MRGN Labs
Author-email: man0s <95379755+losman0s@users.noreply.github.com>
Maintainer-email: man0s <95379755+losman0s@users.noreply.github.com>
Requires-Python: >=3.9, <3.11
Project-URL: repository, https://https://github.com/mrgnlabs/marginfi-sdk/tree/main/python/marginpy
Project-URL: homepage, https://https://github.com/mrgnlabs/marginfi-sdk/tree/main/python/marginpy
